sklandcore/__init__.py
sklandcore/api/__init__.py
sklandcore/api/game.py
sklandcore/auth/__init__.py
sklandcore/auth/hypergryph.py
sklandcore/auth/skland.py
sklandcore/auth/u8.py
sklandcore/byd_client.py
sklandcore/constants.py
sklandcore/did.py
sklandcore/did_manager.py
sklandcore/exceptions.py
sklandcore/models/__init__.py
sklandcore/models/auth.py
sklandcore/models/base.py
sklandcore/models/game.py
sklandcore/models/u8.py
sklandcore/platform.py
sklandcore/signature.py
sklandcore/skd_client.py
sklandcore/wechat_qecode/.gitignore
sklandcore/wechat_qecode/LICENSE
sklandcore/wechat_qecode/README.md
sklandcore/wechat_qecode/__init__.py
sklandcore/wechat_qecode/detect.caffemodel
sklandcore/wechat_qecode/detect.prototxt
sklandcore/wechat_qecode/qrcode.py
sklandcore/wechat_qecode/sr.caffemodel
sklandcore/wechat_qecode/sr.prototxt
sklandcore-0.0.2.dist-info/WHEEL
sklandcore-0.0.2.dist-info/METADATA
sklandcore-0.0.2.dist-info/RECORD
