Metadata-Version: 2.3
Name: SklandCore
Version: 0.0.2
Summary: 
Author: baiqwerdvd
Author-email: baiqwerdvd <158065462+baiqwerdvd@users.noreply.github.com>
License: GPL-3.0-or-later
Requires-Dist: httpx>=0.28.1
Requires-Dist: loguru>=0.7.3
Requires-Dist: opencv-contrib-python>=4.13.0.90
Requires-Dist: pycryptodome>=3.23.0
Requires-Dist: pydantic>=2.12.5
Requires-Python: >=3.10, <4.0
